plover_run_applescript/__init__.py
plover_run_applescript/extension.py
plover_run_applescript/applescript/__init__.py
plover_run_applescript/applescript/script.py
plover_run_applescript/config/__init__.py
plover_run_applescript/config/extractor.py
plover_run_applescript/config/file.py
plover_run_applescript/config/loader.py
plover_run_applescript/config/transformer.py
plover_run_applescript/path/__init__.py
plover_run_applescript/path/expander.py
plover_run_applescript-0.3.13.dist-info/LICENSE.txt
plover_run_applescript-0.3.13.dist-info/METADATA
plover_run_applescript-0.3.13.dist-info/WHEEL
plover_run_applescript-0.3.13.dist-info/entry_points.txt
plover_run_applescript-0.3.13.dist-info/top_level.txt
plover_run_applescript-0.3.13.dist-info/zip-safe
plover_run_applescript-0.3.13.dist-info/RECORD
