Metadata-Version: 2.1
Name: plover_run_applescript
Version: 0.3.13
Summary: Run AppleScripts from Plover
Home-page: https://github.com/paulfioravanti/plover-run-applescript
Author: Paul Fioravanti
Author-email: paul@paulfioravanti.com
License: GNU General Public License v3 or later (GPLv3+)
Keywords: plover plover_plugin
Classifier: Development Status :: 4 - Beta
Classifier: Environment :: Plugins
Classifier: Intended Audience :: End Users/Desktop
Classifier: License :: OSI Approved :: GNU General Public License v3 or later (GPLv3+)
Classifier: Operating System :: MacOS :: MacOS X
Classifier: Programming Language :: Python :: 3
Classifier: Programming Language :: Python :: 3.9
License-File: LICENSE.txt
Requires-Dist: plover >=4.0.0.dev12
Requires-Dist: mac-pyxa ==0.0.9
Provides-Extra: test
Requires-Dist: coverage ; extra == 'test'
Requires-Dist: mac-pyxa ==0.0.9 ; extra == 'test'
Requires-Dist: mypy ; extra == 'test'
Requires-Dist: pylint ; extra == 'test'
Requires-Dist: pytest ; extra == 'test'
Requires-Dist: pytest-cov ; extra == 'test'
Requires-Dist: pytest-mock ; extra == 'test'
